pyslk/__init__.py
pyslk/config.py
pyslk/constants.py
pyslk/pyslk_exceptions.py
pyslk/pyslk_warnings.py
pyslk/retry.py
pyslk/utils.py
pyslk/version.py
pyslk/base/__init__.py
pyslk/base/file_group.py
pyslk/base/group_collection.py
pyslk/base/listing.py
pyslk/base/login.py
pyslk/base/resource_path.py
pyslk/base/searching.py
pyslk/base/stati.py
pyslk/base/versioning.py
pyslk/core/__init__.py
pyslk/core/gen_queries.py
pyslk/core/gfbt.py
pyslk/core/metadata.py
pyslk/core/resource.py
pyslk/core/resource_extras.py
pyslk/core/storage.py
pyslk/jobs/__init__.py
pyslk/jobs/basic.py
pyslk/jobs/submitted_jobs.py
pyslk/jobs/verify.py
pyslk/raw/__init__.py
pyslk/raw/jobs.py
pyslk/raw/jobs_verify.py
pyslk/raw/listing.py
pyslk/raw/login.py
pyslk/raw/metadata.py
pyslk/raw/resource.py
pyslk/raw/search.py
pyslk/raw/storage.py
pyslk/raw/transfer.py
pyslk/raw/versioning.py
pyslk/transfer/__init__.py
pyslk/transfer/archive.py
pyslk/transfer/recall.py
pyslk/transfer/retrieve.py
pyslk-2.3.0.dist-info/licenses/AUTHORS.rst
pyslk-2.3.0.dist-info/licenses/LICENCE
pyslk-2.3.0.dist-info/METADATA
pyslk-2.3.0.dist-info/WHEEL
pyslk-2.3.0.dist-info/top_level.txt
pyslk-2.3.0.dist-info/RECORD
