Metadata-Version: 2.4
Name: pyslk
Version: 2.3.0
Summary: Python library for interaction with the DKRZ tape archive based on non-public CLIs slk and slk_helpers
Author: Bilir, Dogus Kaan (DKRZ), Buntemeyer, Lars (GERICS), Bergemann, Martin (DKRZ), Ehbrecht, Carsten (DKRZ)
Author-email: "Heydebreck, Daniel (DKRZ)" <support@dkrz.de>
Maintainer-email: "Heydebreck, Daniel (DKRZ)" <support@dkrz.de>
License: Simple Python wrapper for `slk` and `slk_helpers`. `slk` is the command line
Project-URL: Homepage, https://gitlab.dkrz.de/hsm-tools/pyslk
Project-URL: Documentation, https://hsm-tools.gitlab-pages.dkrz.de/pyslk/index.html
Project-URL: Repository, https://gitlab.dkrz.de/hsm-tools/pyslk.git
Project-URL: Issues, https://gitlab.dkrz.de/hsm-tools/pyslk/-/issues
Project-URL: Changelog, https://hsm-tools.gitlab-pages.dkrz.de/pyslk/CHANGES.html
Classifier: Programming Language :: Python :: 3
Classifier: License :: OSI Approved :: BSD License
Classifier: Operating System :: OS Independent
Classifier: Development Status :: 5 - Production/Stable
Requires-Python: >=3.9
License-File: LICENCE
License-File: AUTHORS.rst
Requires-Dist: pandas>=1.4.0
Requires-Dist: psutil
Requires-Dist: python-dateutil>=2.8.2
Requires-Dist: tenacity>=8.0.1
Provides-Extra: tests
Requires-Dist: pytest>=7.0.0; extra == "tests"
Requires-Dist: black[jupyter]; extra == "tests"
Requires-Dist: flake8; extra == "tests"
Requires-Dist: isort; extra == "tests"
Requires-Dist: pre-commit; extra == "tests"
Provides-Extra: doc
Requires-Dist: sphinx>=4.2.0; extra == "doc"
Requires-Dist: sphinx-book-theme; extra == "doc"
Requires-Dist: numpydoc; extra == "doc"
Requires-Dist: mock; extra == "doc"
Requires-Dist: myst_parser; extra == "doc"
Provides-Extra: package
Requires-Dist: conda-build; extra == "package"
Requires-Dist: build; extra == "package"
Requires-Dist: setuptools>=61.0; extra == "package"
Requires-Dist: pip>=22.0.0; extra == "package"
Dynamic: license-file
